auto_uncertainties/__init__.py
auto_uncertainties/__init__.pyi
auto_uncertainties/_version.py
auto_uncertainties/display_format.py
auto_uncertainties/exceptions.py
auto_uncertainties/util.py
auto_uncertainties/numpy/__init__.py
auto_uncertainties/numpy/__init__.pyi
auto_uncertainties/numpy/numpy_wrappers.py
auto_uncertainties/uncertainty/__init__.py
auto_uncertainties/uncertainty/__init__.pyi
auto_uncertainties/uncertainty/uncertainty_containers.py
auto_uncertainties-1.0.0.dist-info/licenses/LICENSE
docs/Makefile
docs/make.bat
docs/source/basic_usage.rst
docs/source/conf.py
docs/source/contribution.rst
docs/source/getting_started.rst
docs/source/index.rst
docs/source/jinja_formatters.py
docs/source/numpy_integration.rst
docs/source/_autoapi_templates/python/class.rst
docs/source/_autoapi_templates/python/data.rst
docs/source/_autoapi_templates/python/function.rst
docs/source/_autoapi_templates/python/method.rst
docs/source/_autoapi_templates/python/property.rst
docs/source/_autoapi_templates/python/typealias.rst
docs/source/_autoapi_templates/python/typevar.rst
hooks/fix_line_endings.py
hooks/generate_init.py
paper/paper.bib
paper/paper.md
paper/removed_sections.md
tests/test_display_format.py
tests/test_uncertainty.py
tests/test_util.py
tests/numpy/test_numpy_wrap.py
auto_uncertainties-1.0.0.dist-info/METADATA
auto_uncertainties-1.0.0.dist-info/WHEEL
auto_uncertainties-1.0.0.dist-info/top_level.txt
auto_uncertainties-1.0.0.dist-info/RECORD
