Metadata-Version: 2.4
Name: auto_uncertainties
Version: 1.0.0
Summary: Linear Uncertainty Propagation with Auto-Differentiation
Author-email: Varchas Gopalaswamy <vgop@lle.rochester.edu>, Ethan Mentzer <ementzer@u.rochester.edu>
Classifier: Programming Language :: Python :: 3
Classifier: License :: OSI Approved :: GNU General Public License v3 or later (GPLv3+)
Requires-Python: >=3.11
License-File: LICENSE
Requires-Dist: numpy>=1.23.0
Requires-Dist: jax>=0.3.14
Requires-Dist: jaxlib>=0.3.14
Requires-Dist: joblib>=1.2.0
Requires-Dist: loguru>=0.6.0
Requires-Dist: lazy_loader==0.4
Provides-Extra: ci
Requires-Dist: pytest; extra == "ci"
Requires-Dist: pytest-cov; extra == "ci"
Requires-Dist: hypothesis; extra == "ci"
Requires-Dist: pylint; extra == "ci"
Requires-Dist: pint; extra == "ci"
Provides-Extra: pandas
Requires-Dist: pandas>=1.5.1; extra == "pandas"
Provides-Extra: docs
Requires-Dist: sphinx>=4.1.2; extra == "docs"
Requires-Dist: sphinx_rtd_theme>=1.0.0; extra == "docs"
Requires-Dist: sphinxcontrib-bibtex>=2.3.1; extra == "docs"
Requires-Dist: sphinxcontrib-napoleon>=0.7; extra == "docs"
Requires-Dist: sphinx-autodoc-typehints; extra == "docs"
Requires-Dist: sphinx-copybutton; extra == "docs"
Requires-Dist: sphinx-design; extra == "docs"
Requires-Dist: graphviz; extra == "docs"
Requires-Dist: sphinx-autoapi; extra == "docs"
Requires-Dist: furo; extra == "docs"
Dynamic: license-file
